[
  {
    "id": "https://www.zhihu.com/pin/1976952706968080859",
    "title": "乌克兰国防军在11.25日晚对俄罗斯罗斯托…",
    "date": "2025-11-26",
    "platform": "Zhihu",
    "url": "https://www.zhihu.com/pin/1976952706968080859",
    "image": "https://pic1.zhimg.com/50/v2-058efd2c2536ec29adb14865ad4c75ae.jpg",
    "tags": [],
    "excerpt": "乌克兰国防军在11.25日晚对俄罗斯罗斯托夫州塔干罗格空军基地的联合打击中摧毁了A-100LL预警机和A-60机载激光武器实验平台。 该信息已由乌克兰武装部队总参谋部和乌克兰无人系统部队的报告证实，最新卫星图（图2/3）也证明了该消息的真实性。 卫星图像显示，A-100LL和A-60均受到不可修复的损伤，塔干罗格空军基地别里耶夫设计局总装车间（图2白圈）也受"
  },
  {
    "id": "https://www.zhihu.com/pin/1976588699044184086",
    "title": "来自@AudaxonX (via X)的定位已经证实我…",
    "date": "2025-11-25",
    "platform": "Zhihu",
    "url": "https://www.zhihu.com/pin/1976588699044184086",
    "image": "https://pic2.zhimg.com/50/v2-3f60a5d9a8f825caab369e5d46cfffc4.jpg",
    "tags": [],
    "excerpt": "来自@AudaxonX (via X)的定位已经证实我们昨天对康斯坦丁尼夫卡方向的报告（ 康斯坦丁尼夫卡前线：俄军新战略与激烈战斗 ）： 乌克兰国防军在Oleksandro-Shultyne方向进行了成功的反击并将俄军从定居点西部推离，详细内容见上文链接。 该地区的成功行动将在康斯坦丁尼夫卡东南部的俄军阵地与其稳定控制区隔绝，并进一步限制俄军向康斯坦丁尼夫卡"
  },
  {
    "id": "https://www.zhihu.com/pin/1976556419303100577",
    "title": "425突击团官方频道发布的视频已证实我们…",
    "date": "2025-11-25",
    "platform": "Zhihu",
    "url": "https://www.zhihu.com/pin/1976556419303100577",
    "image": "https://pic2.zhimg.com/50/v2-847780d0f7243d3444a47bd9eb78d7f3.jpg",
    "tags": [],
    "excerpt": "425突击团官方频道发布的视频已证实我们在11.22-11.23的地图更新（链接见文末）。 乌克兰国防军已经重新控制了E-50公路城市段北部的大部分区域、波克罗夫斯克火车站、Soborny广场和波克罗夫斯克师范学校，该报道已由乌克兰国防军第7空降军（链接1）和TSN战地记者Yulia Kyriyenko（链接2）证实。 对425突击团官方视频的最新定位（链接"
  },
  {
    "id": "https://www.zhihu.com/pin/1976185136237277684",
    "title": "康斯坦丁尼夫卡战役已随着9月初俄军对城…",
    "date": "2025-11-23",
    "platform": "Zhihu",
    "url": "https://www.zhihu.com/pin/1976185136237277684",
    "image": "https://pic3.zhimg.com/50/v2-573f17ae22c7230c1536e9aea34f6df1.jpg",
    "tags": [],
    "excerpt": "康斯坦丁尼夫卡战役已随着9月初俄军对城市的第一次渗透开始，而恰索夫亚尔战役也已持续了1年07个月之久，侧翼恰索夫亚尔的失败让俄军在康斯坦丁尼夫卡的正面进攻中承受了巨大损失，并迫使其改变计划。 在昨天的地图更新中（链接见文末），我们已经澄清了康斯坦丁尼夫卡附近的前线，今天我们将聚焦这个在所有前线战斗第二或第三激烈的方向，并对该方向的情况进行进一步补充。 在8月"
  },
  {
    "id": "https://www.zhihu.com/pin/1973728613900777309",
    "title": "我们收到部分用户反馈的需要手动刷新并校…",
    "date": "2025-11-17",
    "platform": "Zhihu",
    "url": "https://www.zhihu.com/pin/1973728613900777309",
    "image": "https://pic2.zhimg.com/50/v2-6ca9a943fb200bb4c14196034c8c77d3.jpg",
    "tags": [],
    "excerpt": "我们收到部分用户反馈的需要手动刷新并校对左上角日期才能确定是否有最新更新可用的问题，因此 我们新增了更新提示功能。 如图所示，如果你在有最新更新可用的时候再次打开地图，更新概要按钮（🔔）将出现红点以提示存在新日期，现在你可以通过点击最新的更新该要、点击“后一天”或点击“跳转到最新”按钮切换到最新前线（不会自动跳转最新！）。 如果这是你首次或在新设备/新浏览"
  },
  {
    "id": "https://www.zhihu.com/pin/1973477372935296955",
    "title": "正如我们在正文中描述的，鉴于M-30补给线…",
    "date": "2025-11-16",
    "platform": "Zhihu",
    "url": "https://www.zhihu.com/pin/1973477372935296955",
    "image": "https://pic1.zhimg.com/50/v2-fb5a77ac372666229c78a9228a59158a.jpg",
    "tags": [],
    "excerpt": "正如我们在正文中描述的，鉴于M-30补给线附近的激烈战斗和它对俄军向城市内部增援对重要性，乌克兰空军在昨天已将该路线上的桥梁炸毁（图片见评论），该桥梁距离前线约1.5公里。 转发原文 ： Kalyna OSINT ： 10.15至今，我们正在互动地图持续更新波克罗夫斯克方向的情况，你可以从官网进入： Kalyna OSINT官方网站已上线 波克罗夫斯克市区内"
  },
  {
    "id": "https://www.zhihu.com/pin/1973463664523772936",
    "title": "我们在10.29日对波克罗夫斯克的报告中提…",
    "date": "2025-11-16",
    "platform": "Zhihu",
    "url": "https://www.zhihu.com/pin/1973463664523772936",
    "image": "https://pic1.zhimg.com/50/v2-f667c23a795db7e33493c9e0a56791db.jpg",
    "tags": [],
    "excerpt": "我们在10.29日对波克罗夫斯克的报告中提到：“负责该方向的至少一个旅的指挥层再次做出了错误的决定并导致这一方向及城市西部的情况进一步恶化。” 乌克兰信息通讯社Vchasno（2025）引用TSN战地记者 Yulia Kyriyenko对该事件进行了详细报道：“俄军是通过 32 旅的火力阵地进入波克罗夫斯克，指挥官可能没及时告知邻军。” 出于一些原因，当时我"
  },
  {
    "id": "https://www.zhihu.com/pin/1972742432551633389",
    "title": "在上一次的更新中，我们详细讨论了在发布…",
    "date": "2025-11-14",
    "platform": "Zhihu",
    "url": "https://www.zhihu.com/pin/1972742432551633389",
    "image": "https://pic3.zhimg.com/50/v2-d6652b72fd5d79081a65156f04f87cb8.jpg",
    "tags": [],
    "excerpt": "在上一次的更新中，我们详细讨论了在发布信息时考虑作战安全（OPSEC）的重要性以及其如何导致乌克兰国防军士兵进入波克罗夫斯克的风险进一步增加。 俄军的遭遇已向我们证实这一点，“莫斯科宣传家正在为波克罗夫斯克入口大量烧毁的装备和伤亡而歇斯底里：几天前泄露的视频显示俄罗斯士兵在大雾中进入波克罗夫斯克，乌克兰随机对该路口发动打击，并导致下一批试图从该路线进入的单位"
  },
  {
    "id": "https://www.zhihu.com/pin/1972630556148765817",
    "title": "自成立以来，我们多次与一些用户产生分歧",
    "date": "2025-11-14",
    "platform": "Zhihu",
    "url": "https://www.zhihu.com/pin/1972630556148765817",
    "image": "",
    "tags": [],
    "excerpt": "自成立以来，我们多次与一些用户产生分歧。除了一部分莫斯科的喉舌和拥趸外，也包括部分乌克兰支持者。 需要特别提到的是 @波特图 。我们在转发他的帖子并提示正确引用后，与其产生了原则上的分歧。经过协商，我们深刻意识到，下述即将探讨和批判的现象并非个例。 作为开源情报分析小组，我们始终坚持维护每一位OSINTer的版权，这是由于不论是不是我们的成员，我们都是开源情"
  },
  {
    "id": "https://www.zhihu.com/pin/1972044126309554022",
    "title": "由于大多数OSINT博主主要于外部社交平台…",
    "date": "2025-11-12",
    "platform": "Zhihu",
    "url": "https://www.zhihu.com/pin/1972044126309554022",
    "image": "https://pic3.zhimg.com/50/v2-0da3446997c647e5a8b0b13de975c0f3.jpg",
    "tags": [],
    "excerpt": "由于大多数OSINT博主主要于外部社交平台发布信息，因此，为了便于国内读者及时获取相关信息，转发和引用都是很有必要的。但作为OSINT团队，我们倡议，对于相关的分析信息与报告的转载，需要为读者提供内容或者内容摘要，并给出相关的信源链接。 我们开发和提供的工具均免费公开使用，但是在任何需要公开的使用中必须明确引用作者或制作团队。 否则，我们可能会对相关内容提出"
  }
]